task_helpers/__init__.py
task_helpers/creators.py
task_helpers/exceptions.py
task_helpers/tasks.py
task_helpers/backends/__init__.py
task_helpers/backends/async_/__init__.py
task_helpers/backends/async_/base.py
task_helpers/backends/async_/redis.py
task_helpers/backends/sync/__init__.py
task_helpers/backends/sync/base.py
task_helpers/backends/sync/redis.py
task_helpers/compressors/__init__.py
task_helpers/compressors/backends/__init__.py
task_helpers/compressors/backends/bzip2.py
task_helpers/compressors/backends/gzip.py
task_helpers/compressors/backends/lz4.py
task_helpers/compressors/backends/lzma.py
task_helpers/compressors/backends/plug.py
task_helpers/compressors/backends/snappy.py
task_helpers/compressors/backends/zlib.py
task_helpers/compressors/backends/zstd.py
task_helpers/compressors/core/__init__.py
task_helpers/compressors/core/base.py
task_helpers/compressors/core/enums.py
task_helpers/compressors/core/exceptions.py
task_helpers/compressors/core/factory.py
task_helpers/converters/__init__.py
task_helpers/converters/base.py
task_helpers/converters/custom_type.py
task_helpers/converters/perform_task_error.py
task_helpers/converters/stub.py
task_helpers/converters/task.py
task_helpers/converters/bytes/__init__.py
task_helpers/converters/bytes/base.py
task_helpers/converters/bytes/msgpack.py
task_helpers/converters/bytes/pickle.py
task_helpers/couriers/__init__.py
task_helpers/couriers/async_.py
task_helpers/couriers/mixins.py
task_helpers/couriers/sync.py
task_helpers/serializers/__init__.py
task_helpers/serializers/base.py
task_helpers/serializers/custom_type.py
task_helpers/serializers/task.py
task_helpers-2.0.0.dist-info/licenses/LICENSE
task_helpers-2.0.0.dist-info/METADATA
task_helpers-2.0.0.dist-info/WHEEL
task_helpers-2.0.0.dist-info/top_level.txt
task_helpers-2.0.0.dist-info/RECORD
